sublister.py
sublister/sublister.py
sublister-1.0.dist-info/METADATA
sublister-1.0.dist-info/WHEEL
sublister-1.0.dist-info/entry_points.txt
sublister-1.0.dist-info/top_level.txt
sublister-1.0.dist-info/RECORD
