Metadata-Version: 2.1
Name: sublister
Version: 1.0
Summary: A tool to find subdomains passively
Home-page: https://github.com/42zen/sublister
Author: Mathias Bochet (aka Zen)
Requires-Dist: requests
Requires-Dist: beautifulsoup4
Requires-Dist: fake-useragent
Requires-Dist: python-dotenv
